mt_dataset/__init__.py
mt_dataset/dataset.py
mt_dataset/download.py
mtb/__init__.py
mtb/dataset.py
mtb/download.py
mtbenchmark-1.0.0.dist-info/LICENSE
mtbenchmark-1.0.0.dist-info/METADATA
mtbenchmark-1.0.0.dist-info/WHEEL
mtbenchmark-1.0.0.dist-info/top_level.txt
mtbenchmark-1.0.0.dist-info/RECORD
