Metadata-Version: 2.1
Name: mtbenchmark
Version: 1.0.0
Summary: A time-series prediction benchmarking tool tailored to enterprise scenarios.
Home-page: https://github.com/AgentGuo/MTB
Author: AgentGuo
Author-email: 841796600@example.com
Classifier: Programming Language :: Python :: 3
Classifier: License :: OSI Approved :: MIT License
Classifier: Operating System :: OS Independent
Requires-Python: >=3.6
License-File: LICENSE
Requires-Dist: torch (>=1.10)
Requires-Dist: numpy (>=1.18)
Requires-Dist: pandas (>=1.2)
Requires-Dist: gdown (>=5.0)
